resens/__init__.py
resens/__version__.py
resens/analysis.py
resens/io.py
resens/processing.py
resens/rasteroptions.py
resens/utils.py
resens-0.4.3.22.dist-info/LICENSE.rst
resens-0.4.3.22.dist-info/METADATA
resens-0.4.3.22.dist-info/WHEEL
resens-0.4.3.22.dist-info/top_level.txt
resens-0.4.3.22.dist-info/RECORD
