Metadata-Version: 2.1
Name: resens
Version: 0.4.3.22
Summary: Raster Processing package for Remote Sensing and Earth Observation
Author: Nikos Argyropoulos
Author-email: n.argiropgeo@gmail.com
License: MIT
Requires-Python: >=3.8
License-File: LICENSE.rst
Requires-Dist: fiona==1.9.6
Requires-Dist: fsspec
Requires-Dist: GDAL==3.4.1
Requires-Dist: geopandas>=0.11.1
Requires-Dist: numpy<2
Requires-Dist: opencv-python>=4.6.0.66
Requires-Dist: setuptools
Requires-Dist: wheel>=0.43.0
